pydeform
pydeform/resources
