Metadata-Version: 1.0
Name: python-deform
Version: 0.1.0
Summary: Python client for Deform.io
Home-page: https://github.com/deformio/python-deform/
Author: Gennady Chibisov
Author-email: web-chib@ya.ru
License: MIT
Platform: UNKNOWN
